Metadata-Version: 1.0
Name: gauss-binom-distributions-patwrz
Version: 0.1
Summary: Gaussian and Binomial distributions
Home-page: UNKNOWN
Author: Patrycja Wrzosek
Author-email: UNKNOWN
License: UNKNOWN
Platform: UNKNOWN
